Files related to Project/memory.v
module memory#(parameter RAWIDTH = 2,  CAWIDTH = 4)
(input clk,input rst,input [3:0] CA ,input we,input [7:0] datain,input re,output reg [7:0] dataout);

reg [7:0] memory [15:0];

integer i;

always @(posedge clk)
begin
	if(rst)
	begin
		for(i=0; i <16 ;i=i+1)
			begin
				memory[i] <= 0;

			end
	end
	else
		begin
			if(we)
				memory[CA] <= datain;
		end
end



always @ (posedge clk)
begin
	if(re)
		dataout <= memory[CA];
end

endmodule

Files related to Project/controller1.v
module controller1 (
    input clk,
    input rst,
    output reg status,
    output [7:0] dataout
);
    parameter CAWIDTH = 4;
    parameter RAWIDTH = 2;
    localparam MAXSIZE = (1 << RAWIDTH);  // Replace ** with shift for synthesis
    reg [7:0] orig;

    reg [3:0] state, nextstate;
    reg [CAWIDTH-1:0] CA;
    reg we, re;
    reg [7:0] datain;
    reg [4:0] count;
    reg element_done;
    reg [2:0] element_operation;
    reg fresh_state;
    reg comp_en;
    reg Test;

    // Memory instantiation (assumed to be synthesizable)
    memory u (
        .clk(clk),
        .rst(rst),
        .CA(CA),
        .we(we),
        .datain(datain),
        .re(re),
        .dataout(dataout)
    );

    // State encoding
    localparam W0_UPDOWN = 4'b0000;
    localparam R0_W1_R1_UP = 4'b0001;
    localparam R1_W0_R0_DOWN = 4'b0010;
    localparam R0_UPDOWN_FINAL = 4'b0011;

    // Main state machine logic
    always @(posedge clk or posedge rst) begin
        if (rst) begin
            state <= W0_UPDOWN;
            count <= 0;
            element_operation <= 3'b000;
            fresh_state <= 1;
            Test <= 1;
        end else if (Test) begin
            case (state)
                W0_UPDOWN: begin
                    status <= 0;
                    if (fresh_state) begin
                        CA <= 0;
                        comp_en <= 0;
                        orig <= 8'b0;
                        fresh_state <= 0;
                    end else begin
                        count <= count + 1;
                        CA <= CA + 1;
                    end
                    datain <= 8'b0;
                    we <= 1;
                    re <= 0;
                    if (count == MAXSIZE * MAXSIZE) nextstate <= R0_W1_R1_UP;
                end

                R0_W1_R1_UP: begin
                    status <= 0;
                    if (fresh_state) begin
                        CA <= 0;
                        orig <= 8'b0;
                        comp_en <= 0;
                        fresh_state <= 0;
                    end else if (element_done) begin
                        element_done <= 0;
                        count <= count + 1;
                        CA <= CA + 1;
                    end
                    case (element_operation)
                        3'b000: begin
                            we <= 0;
                            comp_en <= 0;
                            orig <= 8'b0;
                            re <= 1;
                            element_operation <= 3'b001;
                        end
			3'b001: begin
                            orig <= 8'b0;
                            element_operation <= 3'b010;
                        end
                        3'b010: begin
                            comp_en <= 1;
                            orig <= 0;
                            we <= 1;
                            re <= 0;
                            datain <= 8'b11111111;
                            element_operation <= 3'b011;
                        end
			3'b011: begin
                            orig <= 8'b0;
                            element_operation <= 3'b100;
                        end
			3'b100: begin
                             we <= 0;
                            re <= 1;
                            comp_en <= 0;
                            orig <= 8'b0;
                            element_operation <= 3'b101;
                        end
                        3'b101: begin
                            orig <= 8'b11111111;
                            element_operation <= 3'b110;
                        end
			3'b110: begin
                             comp_en <= 1;
                            orig <= 8'b11111111;
                            element_done <= 1;
                            element_operation <= 3'b111;
                        end
                        3'b111: begin
                            orig <= 8'b11111111;
                            element_operation <= 3'b000;
			end
			
                        
                    endcase
                    if (count == MAXSIZE * MAXSIZE) nextstate <= R1_W0_R0_DOWN;
                end

                R1_W0_R0_DOWN: begin
                    status <= 0;
                    if (fresh_state) begin
                        CA <= 15;
                        fresh_state <= 0;
                        comp_en <= 0;
                        orig <= 8'b0;
                    end else if (element_done) begin
                        element_done <= 0;
                        count <= count + 1;
                        CA <= CA - 1;
                    end
                    case (element_operation)
                        3'b000: begin
                            we <= 0;
                            re <= 1;
                            comp_en <= 0;
                            orig <= 8'b0;
                            element_operation <= 3'b001;
                        end
			3'b001: begin
                            
                            element_operation <= 3'b010;
                        end
                        3'b010: begin
                            comp_en <= 1;
                            orig <= 8'b11111111;
                            we <= 1;
                            re <= 0;
                            datain <= 0;
                            element_operation <= 3'b011;
                        end
			3'b011: begin
                            orig <= 8'b11111111;
                            element_operation <= 3'b100;
                        end
                        3'b100: begin
                            we <= 0;
                            re <= 1;
                            comp_en <= 0;
                            orig <= 8'b0;
                            element_operation <= 3'b101;
                        end
			3'b101: begin
                            orig <= 8'b0;
                            element_operation <= 3'b110;
                        end
                        3'b110: begin
                            comp_en <= 1;
                            orig <= 8'b0;
                            element_done <= 1;
                            element_operation <= 3'b111;
                        end
			3'b111: begin
                            orig <= 8'b0;
                            element_operation <= 3'b000;
                        end
                    endcase
                    if (count == MAXSIZE * MAXSIZE) nextstate <= R0_UPDOWN_FINAL;
                end

                R0_UPDOWN_FINAL: begin
                    status <= 0;
                    if (fresh_state) begin
                        comp_en <= 0;
                        orig <= 8'b0;
                        CA <= 0;
                        fresh_state <= 0;
                    end else begin
                        count <= count + 1;
                            CA <= CA + 1;
                    end
                    we <= 0;
                    re <= 1;
                    comp_en <= 1;
                    orig <= 0;
                    if (count == MAXSIZE * MAXSIZE) Test <= 0;
                end
            endcase
        end
    end

    // State transition logic
    always @(nextstate) begin
        if (rst) begin
            state <= W0_UPDOWN;
        end else begin
            state <= nextstate;
        end
    end
    always @(state) begin
    fresh_state <= 1;
    count <= 0;
    comp_en <= 0;
    orig <= 1'b0;
    element_operation<= 0;
    end
    always @(orig,comp_en) begin
    if (orig==8'b0 || orig==8'b11111111) begin
        if (dataout == orig) status <= 0;
        end
    else status<=1;
    end
endmodule

Verilog/tb_bist_memory.v
module tb_bist_memory;
    // Parameters
    parameter CAWIDTH = 4;
    parameter RAWIDTH = 2;
    integer maxsize = 2**RAWIDTH;

    // Testbench signals
    reg clk;
    reg rst;
    wire status;
    wire [7:0] dataout;

    // Instantiate the DUT (Device Under Test)
    controller1 #(
        .CAWIDTH(CAWIDTH),
        .RAWIDTH(RAWIDTH)
    ) dut (
        .clk(clk),
        .rst(rst),
        .status(status),
        .dataout(dataout)
    );

    // Clock generation
    initial begin
        clk = 0;
        forever #5 clk = ~clk;  // 10 ns clock period
    end

    // Test procedure
    initial begin
        // Open a VCD file for waveform analysis
        $dumpfile("tb_bist_memory.vcd");
        // Capture all signals in the testbench and DUT at depth level 2
        $dumpvars(2, tb_bist_memory);

        // Apply reset
        rst = 1;
        #5;  // Hold reset for 10 ns
        rst = 0;

        // Wait for the DUT to complete the test sequence
        wait (!dut.Test);  // Wait until DUT's internal Test goes low

        // Check the final status
        if (status == 1) begin
            $display("Test FAILED with status: %b", status);
        end else begin
            $display("Test PASSED with status: %b", status);
        end

        // End simulation
        $finish;
    end

    // Monitoring DUT internal signals for debug (if accessible)
    initial begin
        // Display state transitions and important signal changes for debug
        $monitor("Time=%0d: state=%b, count=%d, CA=%d, datain=%b, dataout=%b, status=%b",
            $time, dut.state, dut.count, dut.CA, dut.datain, dataout, status);
    end

endmodule

Files related to Project/tb_bist_memory.vcd
$date
    Nov 27, 2024  12:33:25
$end
$version
    TOOL:	xmsim(64)	22.09-s003
$end
$timescale
    1 ns
$end

$scope module tb_bist_memory $end
$var parameter 32 !    CAWIDTH $end
$var parameter 32 "    RAWIDTH $end
$var integer  32 #    maxsize $end
$var reg       1 $    clk $end
$var reg       1 %    rst $end
$var wire      1 &    status  $end
$var wire      8 '    dataout [7:0] $end

$scope module dut $end
$var wire      1 (    clk  $end
$var wire      1 )    rst  $end
$var reg       1 *    status $end
$var wire      8 '    dataout [7:0] $end
$var parameter 32 +    CAWIDTH $end
$var parameter 32 ,    RAWIDTH $end
$var parameter 32 -    MAXSIZE $end
$var reg       8 .    orig [7:0] $end
$var reg       4 /    state [3:0] $end
$var reg       4 0    nextstate [3:0] $end
$var reg       4 1    CA [3:0] $end
$var reg       1 2    we $end
$var reg       1 3    re $end
$var reg       8 4    datain [7:0] $end
$var reg       5 5    count [4:0] $end
$var reg       1 6    element_done $end
$var reg       3 7    element_operation [2:0] $end
$var reg       1 8    fresh_state $end
$var reg       1 9    comp_en $end
$var reg       1 :    Test $end
$var parameter  4 ;    W0_UPDOWN $end
$var parameter  4 <    R0_W1_R1_UP $end
$var parameter  4 =    R1_W0_R0_DOWN $end
$var parameter  4 >    R0_UPDOWN_FINAL $end
$upscope $end

$upscope $end

$enddefinitions $end
$dumpvars
b11 >
b10 =
b1 <
b0 ;
b100 -
b10 ,
b100 +
b10 "
b100 !
b100 #
0$
1%
x&
bx '
0(
1)
x*
b0 .
b0 /
bx 0
bx 1
x2
x3
bx 4
b0 5
x6
b0 7
18
09
1:
$end
#5
1$
0%
0)
1(
0*
b0 1
08
b0 4
12
03
0&
#10
0$
0(
#15
1$
1(
b1 5
b1 1
#20
0$
0(
#25
1$
1(
b10 5
b10 1
#30
0$
0(
#35
1$
1(
b11 5
b11 1
#40
0$
0(
#45
1$
1(
b100 5
b100 1
#50
0$
0(
#55
1$
1(
b101 5
b101 1
#60
0$
0(
#65
1$
1(
b110 5
b110 1
#70
0$
0(
#75
1$
1(
b111 5
b111 1
#80
0$
0(
#85
1$
1(
b1000 5
b1000 1
#90
0$
0(
#95
1$
1(
b1001 5
b1001 1
#100
0$
0(
#105
1$
1(
b1010 5
b1010 1
#110
0$
0(
#115
1$
1(
b1011 5
b1011 1
#120
0$
0(
#125
1$
1(
b1100 5
b1100 1
#130
0$
0(
#135
1$
1(
b1101 5
b1101 1
#140
0$
0(
#145
1$
1(
b1110 5
b1110 1
#150
0$
0(
#155
1$
1(
b1111 5
b1111 1
#160
0$
0(
#165
1$
1(
b10000 5
b0 1
#170
0$
0(
#175
1$
1(
b10001 5
b1 1
b1 0
b1 /
18
b0 5
#180
0$
0(
#185
1$
1(
b0 1
08
02
13
b1 7
#190
0$
0(
#195
1$
1(
b10 7
b0 '
#200
0$
0(
#205
1$
1(
19
12
03
b11111111 4
b11 7
#210
0$
0(
#215
1$
1(
b100 7
#220
0$
0(
#225
1$
1(
02
13
09
b101 7
#230
0$
0(
#235
1$
1(
b11111111 .
b110 7
b11111111 '
1*
1&
#240
0$
0(
#245
1$
1(
0*
19
16
b111 7
0&
#250
0$
0(
#255
1$
1(
06
b1 5
b1 1
b0 7
#260
0$
0(
#265
1$
1(
09
b0 .
b1 7
b0 '
1*
1&
#270
0$
0(
#275
1$
1(
0*
b10 7
0&
#280
0$
0(
#285
1$
1(
19
12
03
b11 7
#290
0$
0(
#295
1$
1(
b100 7
#300
0$
0(
#305
1$
1(
02
13
09
b101 7
#310
0$
0(
#315
1$
1(
b11111111 .
b110 7
b11111111 '
1*
1&
#320
0$
0(
#325
1$
1(
0*
19
16
b111 7
0&
#330
0$
0(
#335
1$
1(
06
b10 5
b10 1
b0 7
#340
0$
0(
#345
1$
1(
09
b0 .
b1 7
b0 '
1*
1&
#350
0$
0(
#355
1$
1(
0*
b10 7
0&
#360
0$
0(
#365
1$
1(
19
12
03
b11 7
#370
0$
0(
#375
1$
1(
b100 7
#380
0$
0(
#385
1$
1(
02
13
09
b101 7
#390
0$
0(
#395
1$
1(
b11111111 .
b110 7
b11111111 '
1*
1&
#400
0$
0(
#405
1$
1(
0*
19
16
b111 7
0&
#410
0$
0(
#415
1$
1(
06
b11 5
b11 1
b0 7
#420
0$
0(
#425
1$
1(
09
b0 .
b1 7
b0 '
1*
1&
#430
0$
0(
#435
1$
1(
0*
b10 7
0&
#440
0$
0(
#445
1$
1(
19
12
03
b11 7
#450
0$
0(
#455
1$
1(
b100 7
#460
0$
0(
#465
1$
1(
02
13
09
b101 7
#470
0$
0(
#475
1$
1(
b11111111 .
b110 7
b11111111 '
1*
1&
#480
0$
0(
#485
1$
1(
0*
19
16
b111 7
0&
#490
0$
0(
#495
1$
1(
06
b100 5
b100 1
b0 7
#500
0$
0(
#505
1$
1(
09
b0 .
b1 7
b0 '
1*
1&
#510
0$
0(
#515
1$
1(
0*
b10 7
0&
#520
0$
0(
#525
1$
1(
19
12
03
b11 7
#530
0$
0(
#535
1$
1(
b100 7
#540
0$
0(
#545
1$
1(
02
13
09
b101 7
#550
0$
0(
#555
1$
1(
b11111111 .
b110 7
b11111111 '
1*
1&
#560
0$
0(
#565
1$
1(
0*
19
16
b111 7
0&
#570
0$
0(
#575
1$
1(
06
b101 5
b101 1
b0 7
#580
0$
0(
#585
1$
1(
09
b0 .
b1 7
b0 '
1*
1&
#590
0$
0(
#595
1$
1(
0*
b10 7
0&
#600
0$
0(
#605
1$
1(
19
12
03
b11 7
#610
0$
0(
#615
1$
1(
b100 7
#620
0$
0(
#625
1$
1(
02
13
09
b101 7
#630
0$
0(
#635
1$
1(
b11111111 .
b110 7
b11111111 '
1*
1&
#640
0$
0(
#645
1$
1(
0*
19
16
b111 7
0&
#650
0$
0(
#655
1$
1(
06
b110 5
b110 1
b0 7
#660
0$
0(
#665
1$
1(
09
b0 .
b1 7
b0 '
1*
1&
#670
0$
0(
#675
1$
1(
0*
b10 7
0&
#680
0$
0(
#685
1$
1(
19
12
03
b11 7
#690
0$
0(
#695
1$
1(
b100 7
#700
0$
0(
#705
1$
1(
02
13
09
b101 7
#710
0$
0(
#715
1$
1(
b11111111 .
b110 7
b11111111 '
1*
1&
#720
0$
0(
#725
1$
1(
0*
19
16
b111 7
0&
#730
0$
0(
#735
1$
1(
06
b111 5
b111 1
b0 7
#740
0$
0(
#745
1$
1(
09
b0 .
b1 7
b0 '
1*
1&
#750
0$
0(
#755
1$
1(
0*
b10 7
0&
#760
0$
0(
#765
1$
1(
19
12
03
b11 7
#770
0$
0(
#775
1$
1(
b100 7
#780
0$
0(
#785
1$
1(
02
13
09
b101 7
#790
0$
0(
#795
1$
1(
b11111111 .
b110 7
b11111111 '
1*
1&
#800
0$
0(
#805
1$
1(
0*
19
16
b111 7
0&
#810
0$
0(
#815
1$
1(
06
b1000 5
b1000 1
b0 7
#820
0$
0(
#825
1$
1(
09
b0 .
b1 7
b0 '
1*
1&
#830
0$
0(
#835
1$
1(
0*
b10 7
0&
#840
0$
0(
#845
1$
1(
19
12
03
b11 7
#850
0$
0(
#855
1$
1(
b100 7
#860
0$
0(
#865
1$
1(
02
13
09
b101 7
#870
0$
0(
#875
1$
1(
b11111111 .
b110 7
b11111111 '
1*
1&
#880
0$
0(
#885
1$
1(
0*
19
16
b111 7
0&
#890
0$
0(
#895
1$
1(
06
b1001 5
b1001 1
b0 7
#900
0$
0(
#905
1$
1(
09
b0 .
b1 7
b0 '
1*
1&
#910
0$
0(
#915
1$
1(
0*
b10 7
0&
#920
0$
0(
#925
1$
1(
19
12
03
b11 7
#930
0$
0(
#935
1$
1(
b100 7
#940
0$
0(
#945
1$
1(
02
13
09
b101 7
#950
0$
0(
#955
1$
1(
b11111111 .
b110 7
b11111111 '
1*
1&
#960
0$
0(
#965
1$
1(
0*
19
16
b111 7
0&
#970
0$
0(
#975
1$
1(
06
b1010 5
b1010 1
b0 7
#980
0$
0(
#985
1$
1(
09
b0 .
b1 7
b0 '
1*
1&
#990
0$
0(
#995
1$
1(
0*
b10 7
0&
#1000
0$
0(
#1005
1$
1(
19
12
03
b11 7
#1010
0$
0(
#1015
1$
1(
b100 7
#1020
0$
0(
#1025
1$
1(
02
13
09
b101 7
#1030
0$
0(
#1035
1$
1(
b11111111 .
b110 7
b11111111 '
1*
1&
#1040
0$
0(
#1045
1$
1(
0*
19
16
b111 7
0&
#1050
0$
0(
#1055
1$
1(
06
b1011 5
b1011 1
b0 7
#1060
0$
0(
#1065
1$
1(
09
b0 .
b1 7
b0 '
1*
1&
#1070
0$
0(
#1075
1$
1(
0*
b10 7
0&
#1080
0$
0(
#1085
1$
1(
19
12
03
b11 7
#1090
0$
0(
#1095
1$
1(
b100 7
#1100
0$
0(
#1105
1$
1(
02
13
09
b101 7
#1110
0$
0(
#1115
1$
1(
b11111111 .
b110 7
b11111111 '
1*
1&
#1120
0$
0(
#1125
1$
1(
0*
19
16
b111 7
0&
#1130
0$
0(
#1135
1$
1(
06
b1100 5
b1100 1
b0 7
#1140
0$
0(
#1145
1$
1(
09
b0 .
b1 7
b0 '
1*
1&
#1150
0$
0(
#1155
1$
1(
0*
b10 7
0&
#1160
0$
0(
#1165
1$
1(
19
12
03
b11 7
#1170
0$
0(
#1175
1$
1(
b100 7
#1180
0$
0(
#1185
1$
1(
02
13
09
b101 7
#1190
0$
0(
#1195
1$
1(
b11111111 .
b110 7
b11111111 '
1*
1&
#1200
0$
0(
#1205
1$
1(
0*
19
16
b111 7
0&
#1210
0$
0(
#1215
1$
1(
06
b1101 5
b1101 1
b0 7
#1220
0$
0(
#1225
1$
1(
09
b0 .
b1 7
b0 '
1*
1&
#1230
0$
0(
#1235
1$
1(
0*
b10 7
0&
#1240
0$
0(
#1245
1$
1(
19
12
03
b11 7
#1250
0$
0(
#1255
1$
1(
b100 7
#1260
0$
0(
#1265
1$
1(
02
13
09
b101 7
#1270
0$
0(
#1275
1$
1(
b11111111 .
b110 7
b11111111 '
1*
1&
#1280
0$
0(
#1285
1$
1(
0*
19
16
b111 7
0&
#1290
0$
0(
#1295
1$
1(
06
b1110 5
b1110 1
b0 7
#1300
0$
0(
#1305
1$
1(
09
b0 .
b1 7
b0 '
1*
1&
#1310
0$
0(
#1315
1$
1(
0*
b10 7
0&
#1320
0$
0(
#1325
1$
1(
19
12
03
b11 7
#1330
0$
0(
#1335
1$
1(
b100 7
#1340
0$
0(
#1345
1$
1(
02
13
09
b101 7
#1350
0$
0(
#1355
1$
1(
b11111111 .
b110 7
b11111111 '
1*
1&
#1360
0$
0(
#1365
1$
1(
0*
19
16
b111 7
0&
#1370
0$
0(
#1375
1$
1(
06
b1111 5
b1111 1
b0 7
#1380
0$
0(
#1385
1$
1(
09
b0 .
b1 7
b0 '
1*
1&
#1390
0$
0(
#1395
1$
1(
0*
b10 7
0&
#1400
0$
0(
#1405
1$
1(
19
12
03
b11 7
#1410
0$
0(
#1415
1$
1(
b100 7
#1420
0$
0(
#1425
1$
1(
02
13
09
b101 7
#1430
0$
0(
#1435
1$
1(
b11111111 .
b110 7
b11111111 '
1*
1&
#1440
0$
0(
#1445
1$
1(
0*
19
16
b111 7
0&
#1450
0$
0(
#1455
1$
1(
06
b10000 5
b0 1
b0 7
#1460
0$
0(
#1465
1$
1(
09
b0 .
b1 7
b10 0
1*
b10 /
1&
18
b0 5
b0 7
#1470
0$
0(
#1475
1$
1(
0*
b1111 1
08
b1 7
0&
#1480
0$
0(
#1485
1$
1(
b10 7
#1490
0$
0(
#1495
1$
1(
19
b11111111 .
12
03
b0 4
b11 7
#1500
0$
0(
#1505
1$
1(
b100 7
#1510
0$
0(
#1515
1$
1(
02
13
09
b0 .
b101 7
1*
1&
#1520
0$
0(
#1525
1$
1(
0*
b110 7
b0 '
0&
#1530
0$
0(
#1535
1$
1(
19
16
b111 7
#1540
0$
0(
#1545
1$
1(
06
b1 5
b1110 1
b0 7
#1550
0$
0(
#1555
1$
1(
09
b1 7
b11111111 '
#1560
0$
0(
#1565
1$
1(
b10 7
#1570
0$
0(
#1575
1$
1(
19
b11111111 .
12
03
b11 7
#1580
0$
0(
#1585
1$
1(
b100 7
#1590
0$
0(
#1595
1$
1(
02
13
09
b0 .
b101 7
1*
1&
#1600
0$
0(
#1605
1$
1(
0*
b110 7
b0 '
0&
#1610
0$
0(
#1615
1$
1(
19
16
b111 7
#1620
0$
0(
#1625
1$
1(
06
b10 5
b1101 1
b0 7
#1630
0$
0(
#1635
1$
1(
09
b1 7
b11111111 '
#1640
0$
0(
#1645
1$
1(
b10 7
#1650
0$
0(
#1655
1$
1(
19
b11111111 .
12
03
b11 7
#1660
0$
0(
#1665
1$
1(
b100 7
#1670
0$
0(
#1675
1$
1(
02
13
09
b0 .
b101 7
1*
1&
#1680
0$
0(
#1685
1$
1(
0*
b110 7
b0 '
0&
#1690
0$
0(
#1695
1$
1(
19
16
b111 7
#1700
0$
0(
#1705
1$
1(
06
b11 5
b1100 1
b0 7
#1710
0$
0(
#1715
1$
1(
09
b1 7
b11111111 '
#1720
0$
0(
#1725
1$
1(
b10 7
#1730
0$
0(
#1735
1$
1(
19
b11111111 .
12
03
b11 7
#1740
0$
0(
#1745
1$
1(
b100 7
#1750
0$
0(
#1755
1$
1(
02
13
09
b0 .
b101 7
1*
1&
#1760
0$
0(
#1765
1$
1(
0*
b110 7
b0 '
0&
#1770
0$
0(
#1775
1$
1(
19
16
b111 7
#1780
0$
0(
#1785
1$
1(
06
b100 5
b1011 1
b0 7
#1790
0$
0(
#1795
1$
1(
09
b1 7
b11111111 '
#1800
0$
0(
#1805
1$
1(
b10 7
#1810
0$
0(
#1815
1$
1(
19
b11111111 .
12
03
b11 7
#1820
0$
0(
#1825
1$
1(
b100 7
#1830
0$
0(
#1835
1$
1(
02
13
09
b0 .
b101 7
1*
1&
#1840
0$
0(
#1845
1$
1(
0*
b110 7
b0 '
0&
#1850
0$
0(
#1855
1$
1(
19
16
b111 7
#1860
0$
0(
#1865
1$
1(
06
b101 5
b1010 1
b0 7
#1870
0$
0(
#1875
1$
1(
09
b1 7
b11111111 '
#1880
0$
0(
#1885
1$
1(
b10 7
#1890
0$
0(
#1895
1$
1(
19
b11111111 .
12
03
b11 7
#1900
0$
0(
#1905
1$
1(
b100 7
#1910
0$
0(
#1915
1$
1(
02
13
09
b0 .
b101 7
1*
1&
#1920
0$
0(
#1925
1$
1(
0*
b110 7
b0 '
0&
#1930
0$
0(
#1935
1$
1(
19
16
b111 7
#1940
0$
0(
#1945
1$
1(
06
b110 5
b1001 1
b0 7
#1950
0$
0(
#1955
1$
1(
09
b1 7
b11111111 '
#1960
0$
0(
#1965
1$
1(
b10 7
#1970
0$
0(
#1975
1$
1(
19
b11111111 .
12
03
b11 7
#1980
0$
0(
#1985
1$
1(
b100 7
#1990
0$
0(
#1995
1$
1(
02
13
09
b0 .
b101 7
1*
1&
#2000
0$
0(
#2005
1$
1(
0*
b110 7
b0 '
0&
#2010
0$
0(
#2015
1$
1(
19
16
b111 7
#2020
0$
0(
#2025
1$
1(
06
b111 5
b1000 1
b0 7
#2030
0$
0(
#2035
1$
1(
09
b1 7
b11111111 '
#2040
0$
0(
#2045
1$
1(
b10 7
#2050
0$
0(
#2055
1$
1(
19
b11111111 .
12
03
b11 7
#2060
0$
0(
#2065
1$
1(
b100 7
#2070
0$
0(
#2075
1$
1(
02
13
09
b0 .
b101 7
1*
1&
#2080
0$
0(
#2085
1$
1(
0*
b110 7
b0 '
0&
#2090
0$
0(
#2095
1$
1(
19
16
b111 7
#2100
0$
0(
#2105
1$
1(
06
b1000 5
b111 1
b0 7
#2110
0$
0(
#2115
1$
1(
09
b1 7
b11111111 '
#2120
0$
0(
#2125
1$
1(
b10 7
#2130
0$
0(
#2135
1$
1(
19
b11111111 .
12
03
b11 7
#2140
0$
0(
#2145
1$
1(
b100 7
#2150
0$
0(
#2155
1$
1(
02
13
09
b0 .
b101 7
1*
1&
#2160
0$
0(
#2165
1$
1(
0*
b110 7
b0 '
0&
#2170
0$
0(
#2175
1$
1(
19
16
b111 7
#2180
0$
0(
#2185
1$
1(
06
b1001 5
b110 1
b0 7
#2190
0$
0(
#2195
1$
1(
09
b1 7
b11111111 '
#2200
0$
0(
#2205
1$
1(
b10 7
#2210
0$
0(
#2215
1$
1(
19
b11111111 .
12
03
b11 7
#2220
0$
0(
#2225
1$
1(
b100 7
#2230
0$
0(
#2235
1$
1(
02
13
09
b0 .
b101 7
1*
1&
#2240
0$
0(
#2245
1$
1(
0*
b110 7
b0 '
0&
#2250
0$
0(
#2255
1$
1(
19
16
b111 7
#2260
0$
0(
#2265
1$
1(
06
b1010 5
b101 1
b0 7
#2270
0$
0(
#2275
1$
1(
09
b1 7
b11111111 '
#2280
0$
0(
#2285
1$
1(
b10 7
#2290
0$
0(
#2295
1$
1(
19
b11111111 .
12
03
b11 7
#2300
0$
0(
#2305
1$
1(
b100 7
#2310
0$
0(
#2315
1$
1(
02
13
09
b0 .
b101 7
1*
1&
#2320
0$
0(
#2325
1$
1(
0*
b110 7
b0 '
0&
#2330
0$
0(
#2335
1$
1(
19
16
b111 7
#2340
0$
0(
#2345
1$
1(
06
b1011 5
b100 1
b0 7
#2350
0$
0(
#2355
1$
1(
09
b1 7
b11111111 '
#2360
0$
0(
#2365
1$
1(
b10 7
#2370
0$
0(
#2375
1$
1(
19
b11111111 .
12
03
b11 7
#2380
0$
0(
#2385
1$
1(
b100 7
#2390
0$
0(
#2395
1$
1(
02
13
09
b0 .
b101 7
1*
1&
#2400
0$
0(
#2405
1$
1(
0*
b110 7
b0 '
0&
#2410
0$
0(
#2415
1$
1(
19
16
b111 7
#2420
0$
0(
#2425
1$
1(
06
b1100 5
b11 1
b0 7
#2430
0$
0(
#2435
1$
1(
09
b1 7
b11111111 '
#2440
0$
0(
#2445
1$
1(
b10 7
#2450
0$
0(
#2455
1$
1(
19
b11111111 .
12
03
b11 7
#2460
0$
0(
#2465
1$
1(
b100 7
#2470
0$
0(
#2475
1$
1(
02
13
09
b0 .
b101 7
1*
1&
#2480
0$
0(
#2485
1$
1(
0*
b110 7
b0 '
0&
#2490
0$
0(
#2495
1$
1(
19
16
b111 7
#2500
0$
0(
#2505
1$
1(
06
b1101 5
b10 1
b0 7
#2510
0$
0(
#2515
1$
1(
09
b1 7
b11111111 '
#2520
0$
0(
#2525
1$
1(
b10 7
#2530
0$
0(
#2535
1$
1(
19
b11111111 .
12
03
b11 7
#2540
0$
0(
#2545
1$
1(
b100 7
#2550
0$
0(
#2555
1$
1(
02
13
09
b0 .
b101 7
1*
1&
#2560
0$
0(
#2565
1$
1(
0*
b110 7
b0 '
0&
#2570
0$
0(
#2575
1$
1(
19
16
b111 7
#2580
0$
0(
#2585
1$
1(
06
b1110 5
b1 1
b0 7
#2590
0$
0(
#2595
1$
1(
09
b1 7
b11111111 '
#2600
0$
0(
#2605
1$
1(
b10 7
#2610
0$
0(
#2615
1$
1(
19
b11111111 .
12
03
b11 7
#2620
0$
0(
#2625
1$
1(
b100 7
#2630
0$
0(
#2635
1$
1(
02
13
09
b0 .
b101 7
1*
1&
#2640
0$
0(
#2645
1$
1(
0*
b110 7
b0 '
0&
#2650
0$
0(
#2655
1$
1(
19
16
b111 7
#2660
0$
0(
#2665
1$
1(
06
b1111 5
b0 1
b0 7
#2670
0$
0(
#2675
1$
1(
09
b1 7
b11111111 '
#2680
0$
0(
#2685
1$
1(
b10 7
#2690
0$
0(
#2695
1$
1(
19
b11111111 .
12
03
b11 7
#2700
0$
0(
#2705
1$
1(
b100 7
#2710
0$
0(
#2715
1$
1(
02
13
09
b0 .
b101 7
1*
1&
#2720
0$
0(
#2725
1$
1(
0*
b110 7
b0 '
0&
#2730
0$
0(
#2735
1$
1(
19
16
b111 7
#2740
0$
0(
#2745
1$
1(
06
b10000 5
b1111 1
b0 7
#2750
0$
0(
#2755
1$
1(
09
b1 7
b11 0
b11 /
18
b0 5
b0 7
#2760
0$
0(
#2765
1$
1(
b0 1
08
19
#2770
0$
0(
#2775
1$
1(
b1 5
b1 1
#2780
0$
0(
#2785
1$
1(
b10 5
b10 1
#2790
0$
0(
#2795
1$
1(
b11 5
b11 1
#2800
0$
0(
#2805
1$
1(
b100 5
b100 1
#2810
0$
0(
#2815
1$
1(
b101 5
b101 1
#2820
0$
0(
#2825
1$
1(
b110 5
b110 1
#2830
0$
0(
#2835
1$
1(
b111 5
b111 1
#2840
0$
0(
#2845
1$
1(
b1000 5
b1000 1
#2850
0$
0(
#2855
1$
1(
b1001 5
b1001 1
#2860
0$
0(
#2865
1$
1(
b1010 5
b1010 1
#2870
0$
0(
#2875
1$
1(
b1011 5
b1011 1
#2880
0$
0(
#2885
1$
1(
b1100 5
b1100 1
#2890
0$
0(
#2895
1$
1(
b1101 5
b1101 1
#2900
0$
0(
#2905
1$
1(
b1110 5
b1110 1
#2910
0$
0(
#2915
1$
1(
b1111 5
b1111 1
#2920
0$
0(
#2925
1$
1(
b10000 5
b0 1
#2930
0$
0(
#2935
1$
1(
b10001 5
b1 1
0:
